plotscanner/GUI.py
plotscanner/__init__.py
plotscanner/data_frame_table.py
plotscanner/geometry.py
plotscanner/grid.py
plotscanner/plotdigitizer.py
plotscanner/trajectory.py
plotscanner/widgets.py
plotscanner/readme_imgs/example.jpg
plotscanner/ui/buttons.ui
plotscanner/ui/plots.ui
plotscanner-0.0.2.dist-info/METADATA
plotscanner-0.0.2.dist-info/WHEEL
plotscanner-0.0.2.dist-info/entry_points.txt
plotscanner-0.0.2.dist-info/top_level.txt
plotscanner-0.0.2.dist-info/RECORD
