Metadata-Version: 2.1
Name: plotscanner
Version: 0.0.2
Summary: The application for digitizing images of plots.
Home-page: https://github.com/IlS0/Plot-digitization
Author-email: silru@internet.ru
License: UNKNOWN
Platform: UNKNOWN
Requires-Dist: matplotlib (>=3.7.1)
Requires-Dist: numpy (>=1.25.0)
Requires-Dist: PyQt5 (>=5.15.9)
Requires-Dist: opencv-python-headless (>=4.7.0.72)
Requires-Dist: pandas (>=1.5.3)
Requires-Dist: openpyxl (>=3.1.2)
